{"loginbox":{"borderColor":"#ffffff","position":"center","style":"tb","labelFontWeight":"500","labelColor":"#20201e","loginBoxShadow":"rgba(99, 99, 99, 0.2) 0px 2px 8px 0px","buttonPosition":"start","backgroundType":"color","backgroundValue":"#ffffff","labelFontSize":"15px","title":"GC Portal","fontsize":"22px","fontweight":"800","titleposition":"center","fontcolor":"#161414","inputFieldAlign":"start","forgotPassPosition":"start","boxWidth":"400px","boxHeight":"350px","boxPadding":"20px","inputFieldWidth":"350px","buttonWidth":"350px","buttonHeight":"45px","inputFieldHeight":"40px","inputFieldBorderColor":"#c1bebe","boxTitlePaddingTb":""},"main":{"split":"false"},"full":{"backgroundType":"image","backgroundValue":"images/loginimages/bermuda-traingle.png"},"logo":{"position":"center","style":"na","value":"HR Portal","fontcolor":"#966c6c","loginboxposition":"center","fontsize":"12","fontweight":"200"}}